probly/__init__.py
probly/data.py
probly/losses.py
probly/metrics.py
probly/plot.py
probly/tasks.py
probly/calibration/__init__.py
probly/calibration/temperature.py
probly/quantification/__init__.py
probly/quantification/classification.py
probly/quantification/regression.py
probly/representation/__init__.py
probly/representation/bayesian.py
probly/representation/conformalprediction.py
probly/representation/dropconnect.py
probly/representation/dropout.py
probly/representation/ensemble.py
probly/representation/predictor.py
probly/representation/predictor_torch.py
probly/representation/representation.py
probly/representation/subensemble.py
probly/representation/classification/__init__.py
probly/representation/classification/credalensembling.py
probly/representation/classification/evidential.py
probly/representation/layers/__init__.py
probly/representation/layers/bayesian.py
probly/representation/layers/dropconnect.py
probly/representation/layers/normalinversegamma.py
probly/representation/regression/__init__.py
probly/representation/regression/evidential.py
probly/traverse_nn/__init__.py
probly/traverse_nn/nn.py
probly/traverse_nn/torch.py
probly/utils/__init__.py
probly/utils/errors.py
probly/utils/probabilities.py
probly/utils/sets.py
probly/utils/torch.py
probly-0.3.1.dist-info/licenses/LICENSE
pytraverse/__init__.py
pytraverse/composition.py
pytraverse/core.py
pytraverse/decorators.py
pytraverse/generic.py
probly-0.3.1.dist-info/METADATA
probly-0.3.1.dist-info/WHEEL
probly-0.3.1.dist-info/top_level.txt
probly-0.3.1.dist-info/RECORD
