Metadata-Version: 2.4
Name: probly
Version: 0.3.1
Summary: Uncertainty Representation and Quantification for Machine Learning
Author: Timo Löhr, Maximilian Muschalik, Clemens Damke, Alireza Javanmardi
Author-email: Paul Hofman <paul.hofman@ifi.lmu.de>
License-Expression: MIT
Project-URL: documentation, https://pwhofman.github.io/probly
Project-URL: source, https://github.com/pwhofman/probly
Project-URL: tracker, https://github.com/pwhofman/probly/issues
Project-URL: changelog, https://github.com/pwhofman/probly/blob/main/CHANGELOG.md
Classifier: Development Status :: 2 - Pre-Alpha
Classifier: Intended Audience :: Developers
Classifier: Intended Audience :: Science/Research
Classifier: Topic :: Scientific/Engineering
Classifier: Topic :: Scientific/Engineering :: Artificial Intelligence
Classifier: Operating System :: Microsoft :: Windows
Classifier: Operating System :: Unix
Classifier: Operating System :: MacOS
Classifier: Programming Language :: Python :: 3
Classifier: Programming Language :: Python :: 3.10
Classifier: Programming Language :: Python :: 3.11
Classifier: Programming Language :: Python :: 3.12
Classifier: Programming Language :: Python :: 3.13
Requires-Python: >=3.12
License-File: LICENSE
Requires-Dist: scipy
Requires-Dist: matplotlib>=3.8.0
Requires-Dist: multimethod>=2.0
Requires-Dist: mpltern
Requires-Dist: numpy>=2.0.0
Requires-Dist: torch>=2.0.0
Requires-Dist: torchvision
Requires-Dist: scikit-learn
Requires-Dist: tqdm
Requires-Dist: joblib
Dynamic: license-file
